myeventstudy/__init__.py
myeventstudy/event_analysis.py
myeventstudy-0.1.4.dist-info/METADATA
myeventstudy-0.1.4.dist-info/WHEEL
myeventstudy-0.1.4.dist-info/top_level.txt
myeventstudy-0.1.4.dist-info/RECORD
