Metadata-Version: 2.1
Name: myeventstudy
Version: 0.1.4
Summary: Python package for event study analysis
Home-page: https://pypi.org/project/myeventstudy/
Author: Qi Yan
Author-email: 953736070@qq.com
License: MIT
Requires-Dist: pandas
Requires-Dist: statsmodels
Requires-Dist: scipy
